LICENSE
MANIFEST.in
README.rst
setup.py
django_zy_polls.egg-info/PKG-INFO
django_zy_polls.egg-info/SOURCES.txt
django_zy_polls.egg-info/dependency_links.txt
django_zy_polls.egg-info/top_level.txt
polls/__init__.py
polls/admin.py
polls/apps.py
polls/models.py
polls/tests.py
polls/urls.py
polls/views.py
polls/static/polls/style.css
polls/static/polls/images/background.png
polls/templates/admin/base_site.html
polls/templates/admin/index.html
polls/templates/polls/detail.html
polls/templates/polls/index.html
polls/templates/polls/results.html