Metadata-Version: 1.1
Name: django-zy-polls
Version: 0.1
Summary: A simple Django app to conduct Web-based polls.
Home-page: http://127.0.0.1:8000/polls/
Author: Wingdi
Author-email: lens_z@163.com
License: BSD License
Platform: UNKNOWN
Classifier: Environment :: Web Environment
Classifier: Framework :: Django
Classifier: Intended Audience :: Developers
Classifier: License :: OSI Approved :: BSD License
Classifier: Operating System :: OS Independent
Classifier: Programming Language :: Python
Classifier: Programming Language :: Python :: 3.5
Classifier: Topic :: Internet :: WWW/HTTP
Classifier: Topic :: Internet :: WWW/HTTP :: Dynamic Content
